g2opy/__init__.py
g2opy/__init__.pyi
g2opy/amd.dll
g2opy/camd.dll
g2opy/ccolamd.dll
g2opy/cholmod.dll
g2opy/colamd.dll
g2opy/cxsparse.dll
g2opy/g2opy.cp310-win_amd64.pyd
g2opy/g2opy.cp311-win_amd64.pyd
g2opy/g2opy.cp312-win_amd64.pyd
g2opy/g2opy.cp313-win_amd64.pyd
g2opy/g2opy.cpython-310-x86_64-linux-gnu.so
g2opy/g2opy.cpython-311-x86_64-linux-gnu.so
g2opy/g2opy.cpython-312-x86_64-linux-gnu.so
g2opy/g2opy.cpython-313-x86_64-linux-gnu.so
g2opy/libgcc_s_seh-1.dll
g2opy/libgfortran-5.dll
g2opy/liblapack.dll
g2opy/libquadmath-0.dll
g2opy/libwinpthread-1.dll
g2opy/openblas.dll
g2opy/suitesparseconfig.dll
g2opy/g2opy/__init__.pyi
g2opy/g2opy/private.pyi
ubicoders_g2opy.libs/libamd-2f772040.so.3.3.3
ubicoders_g2opy.libs/libblas-0ebaf4e9.so.3.12.1
ubicoders_g2opy.libs/libcamd-74f746ad.so.3.3.3
ubicoders_g2opy.libs/libccolamd-fe9029db.so.3.3.4
ubicoders_g2opy.libs/libcholmod-aa1e9de6.so.5.3.0
ubicoders_g2opy.libs/libcolamd-e39dfc5e.so.3.3.4
ubicoders_g2opy.libs/libcxsparse-ae3706dc.so.4.4.1
ubicoders_g2opy.libs/libfmt-8733d1dc.so.9.1.0
ubicoders_g2opy.libs/libfmt-a292aff5.so.10.1.0
ubicoders_g2opy.libs/libgfortran-d253a72b.so.5.0.0
ubicoders_g2opy.libs/libgomp-e4e5c79b.so.1.0.0
ubicoders_g2opy.libs/liblapack-2689958e.so.3.12.1
ubicoders_g2opy.libs/libmvec-450586cc.so.1
ubicoders_g2opy.libs/libspdlog-4a03eabb.so.1.15.1
ubicoders_g2opy.libs/libspdlog-569acab5.so.1.11.0
ubicoders_g2opy.libs/libsuitesparseconfig-fab82587.so.7.8.3
ubicoders_g2opy-2.1.5.dist-info/METADATA
ubicoders_g2opy-2.1.5.dist-info/WHEEL
ubicoders_g2opy-2.1.5.dist-info/top_level.txt
ubicoders_g2opy-2.1.5.dist-info/RECORD
ubicoders_g2opy-2.1.5.dist-info/licenses/LICENSE
