Metadata-Version: 2.4
Name: ubicoders-g2opy
Version: 2.1.5
Summary: g2o: A General Framework for Graph Optimization (Python bindings)
Author: Maintainers
Project-URL: Homepage, https://github.com/ubicoders0/g2o
Project-URL: Repository, https://github.com/ubicoders0/g2o
Requires-Python: >=3.10
License-File: LICENSE
Requires-Dist: numpy>=2
Dynamic: license-file
